sml/__init__.py
sml/cluster/__init__.py
sml/cluster/kmeans.py
sml/cluster/emulations/__init__.py
sml/cluster/emulations/kmeans_emul.py
sml/cluster/tests/__init__.py
sml/cluster/tests/kmeans_test.py
sml/decomposition/__init__.py
sml/decomposition/nmf.py
sml/decomposition/pca.py
sml/decomposition/tsne.py
sml/decomposition/emulations/__init__.py
sml/decomposition/emulations/nmf_emul.py
sml/decomposition/emulations/pca_emul.py
sml/decomposition/emulations/rsvd_pca_emul.py
sml/decomposition/emulations/tsne_emul.py
sml/decomposition/tests/__init__.py
sml/decomposition/tests/nmf_test.py
sml/decomposition/tests/pca_test.py
sml/decomposition/tests/tsne_test.py
sml/ensemble/__init__.py
sml/ensemble/adaboost.py
sml/ensemble/forest.py
sml/ensemble/emulations/__init__.py
sml/ensemble/emulations/adaboost_emul.py
sml/ensemble/emulations/forest_emul.py
sml/ensemble/tests/__init__.py
sml/ensemble/tests/adaboost_test.py
sml/ensemble/tests/forest_test.py
sml/feature_selection/__init__.py
sml/feature_selection/anova_f.py
sml/feature_selection/univariate_selection.py
sml/feature_selection/emulations/__init__.py
sml/feature_selection/emulations/anova_f_emul.py
sml/feature_selection/emulations/chi2_emul.py
sml/feature_selection/tests/__init__.py
sml/feature_selection/tests/anova_f_test.py
sml/feature_selection/tests/chi2_test.py
sml/gaussian_process/__init__.py
sml/gaussian_process/_gpc.py
sml/gaussian_process/kernels.py
sml/gaussian_process/ovo_ovr.py
sml/gaussian_process/emulations/__init__.py
sml/gaussian_process/emulations/gpc_emul.py
sml/gaussian_process/tests/__init__.py
sml/gaussian_process/tests/gpc_test.py
sml/linear_model/__init__.py
sml/linear_model/glm.py
sml/linear_model/logistic.py
sml/linear_model/pla.py
sml/linear_model/quantile.py
sml/linear_model/ridge.py
sml/linear_model/sgd_classifier.py
sml/linear_model/emulations/__init__.py
sml/linear_model/emulations/glm_emul.py
sml/linear_model/emulations/logistic_emul.py
sml/linear_model/emulations/pla_emul.py
sf_sml-0.1.0.dev20250623.dist-info/METADATA
sf_sml-0.1.0.dev20250623.dist-info/WHEEL
sf_sml-0.1.0.dev20250623.dist-info/top_level.txt
sf_sml-0.1.0.dev20250623.dist-info/RECORD
