Metadata-Version: 2.4
Name: sf-sml
Version: 0.1.0.dev20250623
Summary: Secretflow Secure Machine Learning
Home-page: https://github.com/secretflow/spu
Author: SecretFlow Team
Author-email: secretflow-contact@service.alipay.com
License: Apache 2.0
Classifier: Programming Language :: Python :: 3
Classifier: Programming Language :: Python :: 3.10
Classifier: Programming Language :: Python :: 3.11
Requires-Python: >=3.10, <3.12
Requires-Dist: numpy<2,>=1.22.0
Requires-Dist: multiprocess>=0.70.12.2
Requires-Dist: jax[cpu]<=0.4.34,>=0.4.16
Requires-Dist: spu==0.9.4.dev20250618
Requires-Dist: pandas==1.5.3
Requires-Dist: scikit-learn==1.5.2
Provides-Extra: dev
Requires-Dist: pylint; extra == "dev"
Dynamic: author
Dynamic: author-email
Dynamic: classifier
Dynamic: description
Dynamic: description-content-type
Dynamic: home-page
Dynamic: license
Dynamic: provides-extra
Dynamic: requires-dist
Dynamic: requires-python
Dynamic: summary
